vimgpt/__init__.py
vimgpt/cli.py
vimgpt/core.py
vimgpt/langchain_agents/__init__.py
vimgpt/langchain_agents/plan_and_execute.py
vimgpt/langchain_agents/react.py
vimgpt/llm.py
vimgpt/prompts.py
vimgpt/utils.py
vimgpt-0.1.2.dist-info/LICENSE
vimgpt-0.1.2.dist-info/METADATA
vimgpt-0.1.2.dist-info/WHEEL
vimgpt-0.1.2.dist-info/entry_points.txt
vimgpt-0.1.2.dist-info/RECORD
