Metadata-Version: 2.1
Name: vimgpt
Version: 0.1.2
Summary: LLM agent with direct Vim access using neovim/pynvim
License: MIT
Author: nsbradford
Author-email: nsbradford@gmail.com
Requires-Python: >=3.11,<4.0
Classifier: License :: OSI Approved :: MIT License
Classifier: Programming Language :: Python :: 3
Classifier: Programming Language :: Python :: 3.11
Requires-Dist: litellm (==0.1.618)
Requires-Dist: promptlayer (>=0.2.4,<0.3.0)
Requires-Dist: pynvim (==0.4.3)
